odoo10_addon_barcodes_generator_package-10.0.1.0.0-py2.7-nspkg.pth
odoo/addons/barcodes_generator_package/README.rst
odoo/addons/barcodes_generator_package/__init__.py
odoo/addons/barcodes_generator_package/__manifest__.py
odoo/addons/barcodes_generator_package/demo/barcode_rule.xml
odoo/addons/barcodes_generator_package/demo/function.xml
odoo/addons/barcodes_generator_package/demo/ir_sequence.xml
odoo/addons/barcodes_generator_package/demo/product_packaging.xml
odoo/addons/barcodes_generator_package/i18n/fr.po
odoo/addons/barcodes_generator_package/models/__init__.py
odoo/addons/barcodes_generator_package/models/barcode_rule.py
odoo/addons/barcodes_generator_package/models/product_packaging.py
odoo/addons/barcodes_generator_package/static/description/icon.png
odoo/addons/barcodes_generator_package/static/description/product_packaging_sequence_generation.png
odoo/addons/barcodes_generator_package/tests/__init__.py
odoo/addons/barcodes_generator_package/tests/test_barcode_generator.py
odoo/addons/barcodes_generator_package/views/product_packaging.xml
odoo10_addon_barcodes_generator_package-10.0.1.0.0.dist-info/DESCRIPTION.rst
odoo10_addon_barcodes_generator_package-10.0.1.0.0.dist-info/METADATA
odoo10_addon_barcodes_generator_package-10.0.1.0.0.dist-info/RECORD
odoo10_addon_barcodes_generator_package-10.0.1.0.0.dist-info/WHEEL
odoo10_addon_barcodes_generator_package-10.0.1.0.0.dist-info/metadata.json
odoo10_addon_barcodes_generator_package-10.0.1.0.0.dist-info/namespace_packages.txt
odoo10_addon_barcodes_generator_package-10.0.1.0.0.dist-info/top_level.txt
